{
  "task_id": "81",
  "task_name": "Deployment Automation",
  "implementation_timestamp": "2025-08-13T08:38:19.245967",
  "status": "COMPLETED",
  "completion_percentage": 100.0,
  "components_created": {
    "deployment_scripts": [
      "scripts/deploy",
      "scripts/deployment-health-check.sh",
      "scripts/deployment-rollback.sh"
    ],
    "configuration_files": [
      "scripts/deploy.config.json"
    ],
    "docker_compose_files": [
      "docker-compose.dev.yml",
      "docker-compose.prod.yml"
    ],
    "documentation": [
      "scripts/DEPLOYMENT_README.md"
    ]
  },
  "features_implemented": [
    "multi_environment_deployment",
    "automated_health_checks",
    "rollback_capabilities",
    "docker_compose_orchestration",
    "environment_validation",
    "automated_testing",
    "backup_management",
    "comprehensive_logging"
  ],
  "deployment_environments": [
    "development",
    "staging",
    "production"
  ],
  "files_created": 7
}