{
  "task_id": "task_68",
  "task_name": "End-to-End Test Coverage",
  "verification_timestamp": "2025-08-13T04:53:08.524748",
  "status": "COMPLETED",
  "completion_percentage": 100,
  "evidence": [
    "\u2705 Playwright configuration file created",
    "\u2705 E2E directory created: tests/e2e",
    "\u2705 E2E directory created: tests/e2e/specs",
    "\u2705 E2E directory created: tests/e2e/pages",
    "\u2705 E2E directory created: tests/e2e/utils",
    "\u2705 E2E directory created: test-results",
    "\u2705 Page Object Model created: tests/e2e/pages/BasePage.ts",
    "\u2705 Page Object Model created: tests/e2e/pages/LoginPage.ts",
    "\u2705 Page Object Model created: tests/e2e/pages/DashboardPage.ts",
    "\u2705 E2E test file created: tests/e2e/specs/auth/authentication.spec.ts",
    "\u2705 E2E test file created: tests/e2e/specs/chat/chat-functionality.spec.ts",
    "\u2705 E2E test file created: tests/e2e/specs/dashboard/dashboard.spec.ts",
    "\u2705 E2E utility created: tests/e2e/utils/TestUtils.ts",
    "\u2705 E2E utility created: tests/e2e/data/TestData.ts",
    "\u2705 Global setup file created: tests/e2e/global-setup.ts",
    "\u2705 Global setup file created: tests/e2e/global-teardown.ts"
  ],
  "infrastructure_created": [
    "/home/vivi/pixelated/playwright.config.ts"
  ],
  "component_scores": {
    "playwright_config": 20,
    "e2e_directories": 15,
    "page_objects": 20,
    "test_files": 25,
    "utilities": 10,
    "setup_teardown": 10
  },
  "assessment": "EXCELLENT"
}