{
  "sentence_starters": {
    "And so": 2108,
    "And then": 728,
    "And that": 456,
    "So you": 326,
    "So I": 318,
    "So what": 306,
    "So they": 296,
    "So the": 292,
    "And I": 268,
    "And they": 264,
    "So let": 230,
    "So if": 222,
    "And what": 214,
    "And you": 206,
    "All of": 176,
    "And it": 168,
    "But what": 162,
    "They don't": 150,
    "So that": 150,
    "So let's": 148,
    "And that's": 148,
    "If you": 148,
    "And it's": 144,
    "But then": 142,
    "I will": 140,
    "I don't": 138,
    "So it's": 138,
    "It is": 128,
    "You have": 128,
    "And if": 120,
    "And the": 106,
    "I'm going": 106,
    "So now": 104,
    "The next": 102,
    "Now I": 100,
    "So it": 98,
    "This is": 98,
    "So when": 96,
    "That is": 94,
    "Or you": 94,
    "When you": 94,
    "You don't": 92,
    "I am": 92,
    "So a": 90,
    "I have": 88,
    "So there's": 88,
    "I want": 88,
    "You can't": 86,
    "And he": 86,
    "mp3 **Language:**": 84
  },
  "transition_phrases": {
    "So": 5610,
    "And so": 2176,
    "But": 1382,
    "And then": 730,
    "Now": 698,
    "Let me": 64,
    "What happens": 54,
    "One of the things": 16,
    "Think about": 4,
    "What I find": 2,
    "Imagine": 2,
    "The reality is": 2
  },
  "empathy_markers": {
    "Many people": 260,
    "For many": 206,
    "Some of you": 90,
    "I know": 78,
    "I understand": 10,
    "You might feel": 6,
    "That's painful": 2,
    "What you're going through": 2,
    "That's hard": 2,
    "I get it": 2
  },
  "common_phrases": {
    "a lot of": 464,
    "i'm going to": 452,
    "i want to": 356,
    "of complex trauma": 348,
    "and so what": 302,
    "going to be": 294,
    "want you to": 278,
    "i want you": 268,
    "so let me": 268,
    "characteristics of complex": 258,
    "you're going to": 252,
    "i need to": 250,
    "and so they": 236,
    "you have to": 230,
    "what i want": 222,
    "one of the": 216,
    "all of those": 214,
    "all kinds of": 200,
    "not going to": 200,
    "and that is": 200,
    "out of complex": 196,
    "we're going to": 182,
    "all of a": 180,
    "comes out of": 176,
    "complex trauma is": 176,
    "and so you": 172,
    "complex trauma -": 168,
    "trauma - part": 168,
    "in order to": 166,
    "they're going to": 166,
    "going to get": 166,
    "of complex trauma.": 162,
    "don't want to": 158,
    "of a sudden": 156,
    "and then you": 150,
    "from complex trauma": 146,
    "you need to": 146,
    "people from complex": 142,
    "let me give": 140,
    "and so the": 138,
    "are going to": 138,
    "me give you": 136,
    "all the time": 136,
    "want to be": 134,
    "i have to": 132,
    "you have a": 130,
    "in complex trauma": 130,
    "all of that": 126,
    "all the time.": 124,
    "go back to": 122,
    "and so now": 122,
    "is going to": 120,
    "plpvben3kkqoln7ufgkjjxfjhvvys8sfv4_na_the characteristics of": 116,
    "to look at": 116,
    "some of the": 116,
    "be able to": 116,
    "to be a": 116,
    "to understand is": 114,
    "need to be": 114,
    "the end of": 114,
    "they have to": 114,
    "come out of": 112,
    "a little bit": 112,
    "so if you": 112,
    "don't have to": 110,
    "going to take": 108,
    "i don't want": 108,
    "they want to": 108,
    "to try to": 108,
    "the things that": 106,
    "so what happens": 106,
    "have to be": 106,
    "for many people": 104,
    "and so that": 102,
    "i got to": 96,
    "all of the": 96,
    "i don't have": 96,
    "going to do": 96,
    "in a healthy": 94,
    "coming out of": 94,
    "you want to": 94,
    "so that you": 94,
    "let me just": 92,
    "and then they": 92,
    "that's the end": 92,
    "so the first": 90,
    "and so it": 90,
    "it's going to": 90,
    "you begin to": 90,
    "and all of": 88,
    "to be the": 88,
    "lot of people": 88,
    "that you can": 88,
    "that comes out": 86,
    "to have a": 86,
    "important to understand": 86,
    "what happens in": 86,
    "you got to": 86,
    "**language:** en (confidence:": 84,
    "en (confidence: 1.00)": 84
  },
  "analogies": [
    "So imagine that you were going to  your friends place and they've asked you to stay overnight",
    "So think of tying their shoes,  riding a bike, learning to read arithmetic, learning to add and subtract",
    "It's like a muscle where you  go to the gym and you add weight to that muscle",
    "Many people when they think of complex trauma,  they think about what was done to you",
    "But think of it lost control this way",
    "And they just feel very much like an infant again, helpless to do anything for themselves",
    "So I want  you to think of two examples and again see it through the eyes of your children",
    "So you imagine Joseph's hearing his brother  saying this, they're planning to kill him",
    "Can you imagine all of that, what that would have  brought up inside of Joseph",
    "And once we find an activity or a chemical that gives the brain  chemicals that feel like attachment, we go, I think I found a solution",
    "They could put themselves on a  beach in the Caribbean on the ceiling, looking down as if it was happening to  somebody else",
    "So now instead of just seeing  danger, the brain begins to imagine danger",
    "But I imagine danger",
    "They were made to feel like a burden or a pain",
    "You go through the feelings as if they left you forever separation blues",
    "Can you imagine though in a healthy relationship with somebody, did that how tiresome that would become",
    "So you think of a child who's been abandoned and their brain is saying, I never want to be abandoned again",
    "So think of it this way",
    "That feels like a abandonment, and so you get triggered",
    "So back away and think of it this way",
    "And so many think of  this in terms of how their parents try to manipulate them",
    "All you think of is  yourself",
    "So just think of much of our culture today",
    "Everybody feels like a buddy, but nobody's talked about anything  of any significance",
    "You think of team sports",
    "It almost creates these like a pimple  or cult type of culture within the home over another person",
    "And then beyond that, there's all kinds of negative, powerful emotions like anger and  fear that you're trying to keep bottled up and stuffed down so that they don't come out",
    "And so what feels like a loving action is actually a very unloving action",
    "With the person I imagine having a totally different name, life, etc",
    "It's gotten to the point where I imagine these fantasies every single day and have trouble  sleeping if I'm not imagining myself as this other person",
    "I'm afraid to talk to a therapist about it because I'm afraid of what he or she would  think of me, signed dreamer",
    "All of us young, old, we still go into our imaginations and we imagine a different world",
    "We imagine how things could be better",
    "They love to make forts, have tea parties, dress up and imagine that they're somebody  else",
    "And some would even imagine when they played that sport",
    "So they can imagine a different them where everybody loves them",
    "You can imagine yourself being able to execute justice and vengeance on all the people who  are perpetrating injustice",
    "And so you can imagine the tension, they don't know what to talk about",
    "So the first one that Jesus is giving the disciples this, I am going to go and die,  but here's what I'm going to be like after I die",
    "Imagine how helpful that would have been to the disciples",
    "But just think of this meant for Jesus",
    "About all the pain, the rejection, the torture he's going to go through, what it's going  to be like for him, a pain beyond what we can even imagine",
    "So you have to imagine yourself  in a traumatic event",
    "Just think of this",
    "So think of that",
    "And it's a bit like a yo-yo after a while",
    "And once anger is unresolved and turns into resentment,  so if you have a resentment towards somebody and you look at them, you only think of negative about  them",
    "Then this one, they say, and that's others saying to you, they say, all that was a long  time ago, as if you don't need to deal with it today",
    "A relationship without trust is like a car without gas",
    "And when you see a 30-year-old  a 40-year-old still acting like a two-year-old having a temper tantrum  magnified by 50, it's a very sad thing to behold"
  ],
  "examples": [
    "Let's say that you go to  an airport and you have to go to the washroom or a sporting event and you have  to go to a washroom and there's all kinds of people in the bathroom",
    "Think back to bodily  sensations, emotions that you felt",
    "So let's say you just turn 50",
    "Or let's say your child gets married",
    "Or let's say your child moves away from home",
    "Let's say a child grows up in a home where some days when  they cry somebody comes and picks them up and meets their need and comforts them so they get a  very good response",
    "So for example, you might have had a parent who met your physical needs so well",
    "So let's say this child who can set a complex trauma now is you  as an adult and you are going through a change",
    "But let's say again what happens inside of you when fear of change is triggered",
    "Let's say that you're single parenting right now",
    "Then another one, when your partner is away for a couple of days, let's say on a business trip, you go through depression",
    "Let's say I can only see you once a week when you mom's been used to seeing you  every day",
    "So let's say that you've been struggling a lot with anger",
    "Or let's say you meet Mr",
    "And so just for example, a person who is lonely and sad begins to fantasize about having  a little puppy and it just fills their heart with warmth, with love",
    "So let's say you went into the Jets game, the white out",
    "Let's say that you've been asked to tell your story or you are  going to start a new job",
    "So let's say you find somebody and you study them, and you go, I think that's a trustworthy person, and you study them over quite a few months",
    "And so again, let's say you set a boundary with your parents,  and say, you can't keep phoning ten times a day and dropping over to visit without phoning ahead of time",
    "And so let's say they look, they're looking for your insecurities and they find that you really like validation",
    "So let's say you say to a person you've been in a relationship with",
    "So let's say you set a boundary with mum and all of a sudden you get a phone call from your dad  or your sister or your aunt saying why are you treating your mum so cruelly",
    "Let's say that you were sexually abused but your brain picked up that this person who  sexually abused you always smelled of old spice",
    "Let's say that every time you cried as a child, you were punished",
    "Or let's say every time dad got drunk, he became violent and hurt mom or one of the kids",
    "But let's say you don't get enough water  or you get cold",
    "So let's say 30 years ago, you experienced a war",
    "Let's say you were to come into a new program, and when you first come into it, you go,  wow, this is so good, and you see 90 percent of this program is fantastic",
    "Then another one, when your partner is away for a couple of days, let's say on a business trip, you go through depression",
    "Next skill, let's say that you have a lot of anxiety  about coming into a social setting",
    "So let's say there was a time you wouldn't have been able to come  to finding freedom because your anxiety was too great",
    "Let's say that you were sexually abused but your brain picked up that this person who  sexually abused you always smelled of old spice",
    "Let's say that every time you cried as a child, you were punished",
    "Or let's say every time dad got drunk, he became violent and hurt mom or one of the kids",
    "Let's say your belly button age, that's your  birthday, your physical age, is 40 years old",
    "Okay, so let's say that you impulsively eat  or impulsively shop, make yourself accountable to somebody",
    "One another thing that you can do is when you're going,  let's say to the mall or you're going to the grocery store,  mentally prepare yourself in advance  for the possible temptations you'll face",
    "Now let's say you were having trouble sleeping and you went to the doctor  and what would he look for if he was going to diagnose sleep disorder",
    "Okay, so let's say that you impulsively eat  or impulsively shop, make yourself accountable to somebody",
    "One another thing that you can do is when you're going,  let's say to the mall or you're going to the grocery store,  mentally prepare yourself in advance  for the possible temptations you'll face",
    "Let's say your belly button age, that's your  birthday, your physical age, is 40 years old",
    "Now let's say you were having trouble sleeping and you went to the doctor  and what would he look for if he was going to diagnose sleep disorder",
    "So let's say that you've been struggling a lot with anger",
    "They've lost their money or let's say the economy crashes  and they lose their money",
    "But let's say you don't get enough water  or you get cold",
    "So let's say 30 years ago, you experienced a war",
    "Let's say I can only see you once a week when you mom's been used to seeing you  every day",
    "They've lost their money or let's say the economy crashes  and they lose their money",
    "You're back with her and away you go  And you can't be reasoned with  Or let's say your partner  Sits down one night with you and says you know what we're just not working out",
    "And so again, let's say you set a boundary with your parents,  and say, you can't keep phoning ten times a day and dropping over to visit without phoning ahead of time"
  ],
  "teaching_patterns": [
    {
      "pattern": "First",
      "frequency": 446
    },
    {
      "pattern": "Second",
      "frequency": 416
    },
    {
      "pattern": "Third",
      "frequency": 114
    },
    {
      "pattern": "What happens is",
      "frequency": 26
    },
    {
      "pattern": "The reality is",
      "frequency": 10
    },
    {
      "pattern": "What we find",
      "frequency": 18
    },
    {
      "pattern": "One of the key",
      "frequency": 2
    },
    {
      "pattern": "It's important to understand",
      "frequency": 26
    },
    {
      "pattern": "Let me give you an example",
      "frequency": 16
    },
    {
      "pattern": "Think about this",
      "frequency": 6
    }
  ]
}