{
  "epoch": 1,
  "metrics": {
    "epoch": 2,
    "training_loss": 0.6108981373074933,
    "validation_loss": 0.29200530684676973,
    "therapeutic_accuracy": 0.0,
    "safety_score": 0.85,
    "knowledge_integration_score": 0.0,
    "timestamp": "2025-10-23T04:48:00.945135"
  },
  "config": {
    "psychology_knowledge_path": "psychology_knowledge_base.json",
    "voice_transcript_path": ".notes/transcripts",
    "output_model_path": "ai/pixel/models/voice_trained",
    "batch_size": 16,
    "learning_rate": 0.001,
    "epochs": 5,
    "validation_split": 0.2,
    "safety_threshold": 0.8,
    "therapeutic_confidence_threshold": 0.7
  },
  "psychology_knowledge_stats": {
    "concepts": 1101,
    "techniques": 22,
    "experts": 11
  }
}